CS147DVPyParser/AssemblyParser.py
CS147DVPyParser/__init__.py
CS147DVPyParser_rdeamicis-0.0.1.dist-info/LICENSE
CS147DVPyParser_rdeamicis-0.0.1.dist-info/METADATA
CS147DVPyParser_rdeamicis-0.0.1.dist-info/WHEEL
CS147DVPyParser_rdeamicis-0.0.1.dist-info/top_level.txt
CS147DVPyParser_rdeamicis-0.0.1.dist-info/RECORD
