Metadata-Version: 2.1
Name: CS147DVPyParser-rdeamicis
Version: 0.0.1
Summary: A package for converting CS147DV assembly language instructions into hexadecimal code
Home-page: https://github.com/rdeamici/CS147DVParser
Author: Richard DeAmicis
Author-email: rtdeamicis@gmail.com
License: UNKNOWN
Platform: UNKNOWN
Classifier: Programming Language :: Python
Classifier: Programming Language :: Java
Classifier: License :: OSI Approved :: MIT License
Classifier: Operating System :: OS Independent
